helloworld.py
helloworlddvbhat-1.0.dist-info/METADATA
helloworlddvbhat-1.0.dist-info/WHEEL
helloworlddvbhat-1.0.dist-info/top_level.txt
helloworlddvbhat-1.0.dist-info/RECORD
